alignmenter/__init__.py
alignmenter/cli.py
alignmenter/config.py
alignmenter/run_config.py
alignmenter/runner.py
alignmenter/calibration/__init__.py
alignmenter/calibration/analyze.py
alignmenter/calibration/bounds.py
alignmenter/calibration/diagnose.py
alignmenter/calibration/generate.py
alignmenter/calibration/label.py
alignmenter/calibration/optimize.py
alignmenter/calibration/sampling.py
alignmenter/calibration/validate.py
alignmenter/data/configs/demo_config.yaml
alignmenter/data/configs/run.yaml
alignmenter/data/configs/safety_keywords.yaml
alignmenter/data/configs/judges/safety_prompt.txt
alignmenter/data/configs/persona/default.yaml
alignmenter/data/datasets/demo_conversations.jsonl
alignmenter/judges/__init__.py
alignmenter/judges/authenticity_judge.py
alignmenter/judges/prompts.py
alignmenter/providers/__init__.py
alignmenter/providers/anthropic.py
alignmenter/providers/base.py
alignmenter/providers/classifiers.py
alignmenter/providers/embeddings.py
alignmenter/providers/judges.py
alignmenter/providers/local.py
alignmenter/providers/openai.py
alignmenter/reporting/__init__.py
alignmenter/reporting/html.py
alignmenter/reporting/json_out.py
alignmenter/scorers/__init__.py
alignmenter/scorers/authenticity.py
alignmenter/scorers/safety.py
alignmenter/scorers/stability.py
alignmenter/scripts/__init__.py
alignmenter/scripts/bootstrap_dataset.py
alignmenter/scripts/calibrate_persona.py
alignmenter/scripts/run_openai_demo.py
alignmenter/scripts/sanitize_dataset.py
alignmenter/utils/__init__.py
alignmenter/utils/io.py
alignmenter/utils/tokens.py
alignmenter/utils/yaml.py
alignmenter-0.1.2.dist-info/licenses/LICENSE
alignmenter-0.1.2.dist-info/METADATA
alignmenter-0.1.2.dist-info/WHEEL
alignmenter-0.1.2.dist-info/entry_points.txt
alignmenter-0.1.2.dist-info/top_level.txt
alignmenter-0.1.2.dist-info/RECORD
