Metadata-Version: 2.4
Name: alignmenter
Version: 0.1.2
Summary: Persona-aligned evaluation toolkit for auditing conversational AI authenticity, safety, and stability.
Author: Alignmenter
License:                                  Apache License
Project-URL: Homepage, https://alignmenter.com
Project-URL: Repository, https://github.com/justinGrosvenor/alignmenter
Project-URL: Documentation, https://github.com/justinGrosvenor/alignmenter
Project-URL: Bug Tracker, https://github.com/justinGrosvenor/alignmenter/issues
Keywords: llm,evaluation,alignment,persona,safety
Classifier: Development Status :: 3 - Alpha
Classifier: Intended Audience :: Developers
Classifier: Intended Audience :: Information Technology
Classifier: License :: OSI Approved :: Apache Software License
Classifier: Topic :: Scientific/Engineering :: Artificial Intelligence
Classifier: Programming Language :: Python
Classifier: Programming Language :: Python :: 3
Classifier: Programming Language :: Python :: 3.10
Classifier: Programming Language :: Python :: 3.11
Requires-Python: >=3.10
License-File: LICENSE
Requires-Dist: typer[all]
Requires-Dist: pydantic
Requires-Dist: pydantic-settings>=2.0
Requires-Dist: openai>=1.12.0
Requires-Dist: anthropic>=0.18.0
Requires-Dist: scikit-learn>=1.3.0
Requires-Dist: numpy>=1.24.0
Requires-Dist: pyyaml>=6.0
Requires-Dist: sentence-transformers>=2.2.2
Requires-Dist: torch
Requires-Dist: tiktoken>=0.7.0
Requires-Dist: requests>=2.32.0
Provides-Extra: dev
Requires-Dist: pytest; extra == "dev"
Requires-Dist: pytest-cov; extra == "dev"
Requires-Dist: ruff; extra == "dev"
Requires-Dist: build; extra == "dev"
Requires-Dist: twine; extra == "dev"
Provides-Extra: safety
Requires-Dist: transformers>=4.30.0; extra == "safety"
Dynamic: license-file
